[
  {
    "UserName": "mansell.lane@bluefruit.co.uk",
    "TimeStamp": "2023-07-24T14:36:23.1147654+01:00",
    "workItem": {
      "Id": 10,
      "Title": "fdsfsdf",
      "Content": "\u003Cp\u003Efdsfsd\u003C/p\u003E",
      "Status": "Nice bloke",
      "Priority": 0,
      "Effort": 0,
      "Type": 0,
      "Sprint": {
        "Id": 1000,
        "Name": "Sprint 1",
        "StartDate": "2023-02-09T16:34:45.6571429+00:00",
        "EndDate": "2023-02-23T16:34:45.6571766+00:00",
        "Feedback": [],
        "Ratings": [],
        "IsCompleted": false
      },
      "LastUpdated": "0001-01-01T00:00:00",
      "Tags": [],
      "Comments": [],
      "Index": 0,
      "UsersAssigned": [],
      "DefinitionOfDoneChecklistItems": [],
      "TaskChecklist": [],
      "AssignedPullRequests": [],
      "TimeInFlightEntries": [
        {
          "EntryTime": 1690205777,
          "WorkStateId": "Nice bloke"
        }
      ]
    }
  },
  {
    "UserName": "mansell.lane@bluefruit.co.uk",
    "TimeStamp": "2023-07-24T14:36:53.8915787+01:00",
    "workItem": {
      "Id": 10,
      "Title": "fdsfsdf",
      "Content": "\u003Cp\u003Efdsfsd\u003C/p\u003E",
      "Status": "Is",
      "Priority": 0,
      "Effort": 0,
      "Type": 0,
      "Sprint": {
        "Id": 1000,
        "Name": "Sprint 1",
        "StartDate": "2023-02-09T16:34:45.6571429+00:00",
        "EndDate": "2023-02-23T16:34:45.6571766+00:00",
        "Feedback": [],
        "Ratings": [],
        "IsCompleted": false
      },
      "LastUpdated": "0001-01-01T00:00:00",
      "Tags": [],
      "Comments": [],
      "Index": 0,
      "UsersAssigned": [],
      "DefinitionOfDoneChecklistItems": [],
      "TaskChecklist": [],
      "AssignedPullRequests": [],
      "TimeInFlightEntries": [
        {
          "EntryTime": 1690205777,
          "WorkStateId": "Nice bloke"
        },
        {
          "EntryTime": 1690205813,
          "WorkStateId": "Is"
        }
      ]
    }
  },
  {
    "UserName": "mansell.lane@bluefruit.co.uk",
    "TimeStamp": "2023-07-24T14:36:55.9093244+01:00",
    "workItem": {
      "Id": 10,
      "Title": "fdsfsdf",
      "Content": "\u003Cp\u003Efdsfsd\u003C/p\u003E",
      "Status": "A",
      "Priority": 0,
      "Effort": 0,
      "Type": 0,
      "Sprint": {
        "Id": 1000,
        "Name": "Sprint 1",
        "StartDate": "2023-02-09T16:34:45.6571429+00:00",
        "EndDate": "2023-02-23T16:34:45.6571766+00:00",
        "Feedback": [],
        "Ratings": [],
        "IsCompleted": false
      },
      "LastUpdated": "0001-01-01T00:00:00",
      "Tags": [],
      "Comments": [],
      "Index": 0,
      "UsersAssigned": [],
      "DefinitionOfDoneChecklistItems": [],
      "TaskChecklist": [],
      "AssignedPullRequests": [],
      "TimeInFlightEntries": [
        {
          "EntryTime": 1690205777,
          "WorkStateId": "Nice bloke"
        },
        {
          "EntryTime": 1690205813,
          "WorkStateId": "Is"
        },
        {
          "EntryTime": 1690205815,
          "WorkStateId": "A"
        }
      ]
    }
  },
  {
    "UserName": "mansell.lane@bluefruit.co.uk",
    "TimeStamp": "2023-07-24T14:36:56.743269+01:00",
    "workItem": {
      "Id": 10,
      "Title": "fdsfsdf",
      "Content": "\u003Cp\u003Efdsfsd\u003C/p\u003E",
      "Status": "Nice bloke",
      "Priority": 0,
      "Effort": 0,
      "Type": 0,
      "Sprint": {
        "Id": 1000,
        "Name": "Sprint 1",
        "StartDate": "2023-02-09T16:34:45.6571429+00:00",
        "EndDate": "2023-02-23T16:34:45.6571766+00:00",
        "Feedback": [],
        "Ratings": [],
        "IsCompleted": false
      },
      "LastUpdated": "0001-01-01T00:00:00",
      "Tags": [],
      "Comments": [],
      "Index": 0,
      "UsersAssigned": [],
      "DefinitionOfDoneChecklistItems": [],
      "TaskChecklist": [],
      "AssignedPullRequests": [],
      "TimeInFlightEntries": [
        {
          "EntryTime": 1690205777,
          "WorkStateId": "Nice bloke"
        },
        {
          "EntryTime": 1690205813,
          "WorkStateId": "Is"
        },
        {
          "EntryTime": 1690205815,
          "WorkStateId": "A"
        },
        {
          "EntryTime": 1690205816,
          "WorkStateId": "Nice bloke"
        }
      ]
    }
  },
  {
    "UserName": "mansell.lane@bluefruit.co.uk",
    "TimeStamp": "2023-07-24T14:37:02.2775274+01:00",
    "workItem": {
      "Id": 10,
      "Title": "fdsfsdf",
      "Content": "\u003Cp\u003Efdsfsd\u003C/p\u003E",
      "Status": "Is",
      "Priority": 0,
      "Effort": 0,
      "Type": 0,
      "Sprint": {
        "Id": 1000,
        "Name": "Sprint 1",
        "StartDate": "2023-02-09T16:34:45.6571429+00:00",
        "EndDate": "2023-02-23T16:34:45.6571766+00:00",
        "Feedback": [],
        "Ratings": [],
        "IsCompleted": false
      },
      "LastUpdated": "0001-01-01T00:00:00",
      "Tags": [],
      "Comments": [],
      "Index": 0,
      "UsersAssigned": [],
      "DefinitionOfDoneChecklistItems": [],
      "TaskChecklist": [],
      "AssignedPullRequests": [],
      "TimeInFlightEntries": [
        {
          "EntryTime": 1690205777,
          "WorkStateId": "Nice bloke"
        },
        {
          "EntryTime": 1690205813,
          "WorkStateId": "Is"
        },
        {
          "EntryTime": 1690205815,
          "WorkStateId": "A"
        },
        {
          "EntryTime": 1690205816,
          "WorkStateId": "Nice bloke"
        },
        {
          "EntryTime": 1690205822,
          "WorkStateId": "Is"
        }
      ]
    }
  },
  {
    "UserName": "mansell.lane@bluefruit.co.uk",
    "TimeStamp": "2023-07-24T14:37:02.9862914+01:00",
    "workItem": {
      "Id": 10,
      "Title": "fdsfsdf",
      "Content": "\u003Cp\u003Efdsfsd\u003C/p\u003E",
      "Status": "A",
      "Priority": 0,
      "Effort": 0,
      "Type": 0,
      "Sprint": {
        "Id": 1000,
        "Name": "Sprint 1",
        "StartDate": "2023-02-09T16:34:45.6571429+00:00",
        "EndDate": "2023-02-23T16:34:45.6571766+00:00",
        "Feedback": [],
        "Ratings": [],
        "IsCompleted": false
      },
      "LastUpdated": "0001-01-01T00:00:00",
      "Tags": [],
      "Comments": [],
      "Index": 0,
      "UsersAssigned": [],
      "DefinitionOfDoneChecklistItems": [],
      "TaskChecklist": [],
      "AssignedPullRequests": [],
      "TimeInFlightEntries": [
        {
          "EntryTime": 1690205777,
          "WorkStateId": "Nice bloke"
        },
        {
          "EntryTime": 1690205813,
          "WorkStateId": "Is"
        },
        {
          "EntryTime": 1690205815,
          "WorkStateId": "A"
        },
        {
          "EntryTime": 1690205816,
          "WorkStateId": "Nice bloke"
        },
        {
          "EntryTime": 1690205822,
          "WorkStateId": "Is"
        },
        {
          "EntryTime": 1690205822,
          "WorkStateId": "A"
        }
      ]
    }
  },
  {
    "UserName": "mansell.lane@bluefruit.co.uk",
    "TimeStamp": "2023-07-24T14:37:04.0793525+01:00",
    "workItem": {
      "Id": 10,
      "Title": "fdsfsdf",
      "Content": "\u003Cp\u003Efdsfsd\u003C/p\u003E",
      "Status": "Jeffery",
      "Priority": 0,
      "Effort": 0,
      "Type": 0,
      "Sprint": {
        "Id": 1000,
        "Name": "Sprint 1",
        "StartDate": "2023-02-09T16:34:45.6571429+00:00",
        "EndDate": "2023-02-23T16:34:45.6571766+00:00",
        "Feedback": [],
        "Ratings": [],
        "IsCompleted": false
      },
      "LastUpdated": "0001-01-01T00:00:00",
      "Tags": [],
      "Comments": [],
      "Index": 0,
      "UsersAssigned": [],
      "DefinitionOfDoneChecklistItems": [],
      "TaskChecklist": [],
      "AssignedPullRequests": [],
      "TimeInFlightEntries": [
        {
          "EntryTime": 1690205777,
          "WorkStateId": "Nice bloke"
        },
        {
          "EntryTime": 1690205813,
          "WorkStateId": "Is"
        },
        {
          "EntryTime": 1690205815,
          "WorkStateId": "A"
        },
        {
          "EntryTime": 1690205816,
          "WorkStateId": "Nice bloke"
        },
        {
          "EntryTime": 1690205822,
          "WorkStateId": "Is"
        },
        {
          "EntryTime": 1690205822,
          "WorkStateId": "A"
        },
        {
          "EntryTime": 1690205824,
          "WorkStateId": "Jeffery"
        }
      ]
    }
  },
  {
    "UserName": "mansell.lane@bluefruit.co.uk",
    "TimeStamp": "2023-07-24T14:37:05.1948739+01:00",
    "workItem": {
      "Id": 10,
      "Title": "fdsfsdf",
      "Content": "\u003Cp\u003Efdsfsd\u003C/p\u003E",
      "Status": "A",
      "Priority": 0,
      "Effort": 0,
      "Type": 0,
      "Sprint": {
        "Id": 1000,
        "Name": "Sprint 1",
        "StartDate": "2023-02-09T16:34:45.6571429+00:00",
        "EndDate": "2023-02-23T16:34:45.6571766+00:00",
        "Feedback": [],
        "Ratings": [],
        "IsCompleted": false
      },
      "LastUpdated": "0001-01-01T00:00:00",
      "Tags": [],
      "Comments": [],
      "Index": 0,
      "UsersAssigned": [],
      "DefinitionOfDoneChecklistItems": [],
      "TaskChecklist": [],
      "AssignedPullRequests": [],
      "TimeInFlightEntries": [
        {
          "EntryTime": 1690205777,
          "WorkStateId": "Nice bloke"
        },
        {
          "EntryTime": 1690205813,
          "WorkStateId": "Is"
        },
        {
          "EntryTime": 1690205815,
          "WorkStateId": "A"
        },
        {
          "EntryTime": 1690205816,
          "WorkStateId": "Nice bloke"
        },
        {
          "EntryTime": 1690205822,
          "WorkStateId": "Is"
        },
        {
          "EntryTime": 1690205822,
          "WorkStateId": "A"
        },
        {
          "EntryTime": 1690205824,
          "WorkStateId": "Jeffery"
        },
        {
          "EntryTime": 1690205825,
          "WorkStateId": "A"
        }
      ]
    }
  }
]